README.md
chain.py
cutbynoise.py
pyproject.toml
cutbynoise.egg-info/PKG-INFO
cutbynoise.egg-info/SOURCES.txt
cutbynoise.egg-info/dependency_links.txt
cutbynoise.egg-info/entry_points.txt
cutbynoise.egg-info/requires.txt
cutbynoise.egg-info/top_level.txt