Metadata-Version: 2.4
Name: cutbynoise
Version: 0.1.3
Summary: cut sample enclosed noise regions out of sound files
Author-email: Georg Sauthoff <mail@gms.tf>
License-Expression: GPL-3.0-or-later
Project-URL: Homepage, https://github.com/gsauthof/cutbynoise
Project-URL: Issues, https://github.com/gsauthof/cutbynoise/issues
Classifier: Programming Language :: Python :: 3
Classifier: Operating System :: OS Independent
Classifier: Topic :: Multimedia :: Sound/Audio :: Analysis
Classifier: Topic :: Multimedia :: Sound/Audio :: Conversion
Requires-Python: >=3.8
Requires-Dist: numpy
Requires-Dist: scipy
